{
  "cab43653-d489-482d-9084-d81fc1586a4b": {
    "description": null,
    "design_tokens": {
      "border_radius": [
        {
          "description": "No border radius",
          "name": "none",
          "value": "0px"
        },
        {
          "description": "Small border radius",
          "name": "sm",
          "value": "2px"
        },
        {
          "description": "Medium border radius",
          "name": "md",
          "value": "4px"
        },
        {
          "description": "Large border radius",
          "name": "lg",
          "value": "6px"
        },
        {
          "description": "Extra large border radius",
          "name": "xl",
          "value": "12px"
        },
        {
          "description": "Full border radius",
          "name": "full",
          "value": "9999px"
        }
      ],
      "colors": [
        {
          "description": "Lightest primary blue",
          "name": "primary-50",
          "value": "#eff6ff"
        },
        {
          "description": "Very light primary blue",
          "name": "primary-100",
          "value": "#dbeafe"
        },
        {
          "description": "Primary blue",
          "name": "primary-500",
          "value": "#3b82f6"
        },
        {
          "description": "Dark primary blue",
          "name": "primary-600",
          "value": "#2563eb"
        },
        {
          "description": "Darkest primary blue",
          "name": "primary-900",
          "value": "#1e3a8a"
        },
        {
          "description": "Lightest gray",
          "name": "gray-50",
          "value": "#f9fafb"
        },
        {
          "description": "Very light gray",
          "name": "gray-100",
          "value": "#f3f4f6"
        },
        {
          "description": "Light gray",
          "name": "gray-200",
          "value": "#e5e7eb"
        },
        {
          "description": "Medium light gray",
          "name": "gray-300",
          "value": "#d1d5db"
        },
        {
          "description": "Medium gray",
          "name": "gray-400",
          "value": "#9ca3af"
        },
        {
          "description": "Medium dark gray",
          "name": "gray-500",
          "value": "#6b7280"
        },
        {
          "description": "Dark gray",
          "name": "gray-600",
          "value": "#4b5563"
        },
        {
          "description": "Very dark gray",
          "name": "gray-700",
          "value": "#374151"
        },
        {
          "description": "Darkest gray",
          "name": "gray-800",
          "value": "#1f2937"
        },
        {
          "description": "Black gray",
          "name": "gray-900",
          "value": "#111827"
        },
        {
          "description": "Success green",
          "name": "success-500",
          "value": "#10b981"
        },
        {
          "description": "Warning orange",
          "name": "warning-500",
          "value": "#f59e0b"
        },
        {
          "description": "Error red",
          "name": "error-500",
          "value": "#ef4444"
        },
        {
          "description": "Pure white",
          "name": "white",
          "value": "#ffffff"
        },
        {
          "description": "Pure black",
          "name": "black",
          "value": "#000000"
        }
      ],
      "shadows": [
        {
          "description": "No shadow",
          "name": "none",
          "value": "none"
        },
        {
          "description": "Small shadow",
          "name": "sm",
          "value": "0 1px 2px 0 rgb(0 0 0 / 0.05)"
        },
        {
          "description": "Medium shadow",
          "name": "md",
          "value": "0 4px 6px -1px rgb(0 0 0 / 0.1), 0 2px 4px -2px rgb(0 0 0 / 0.1)"
        },
        {
          "description": "Large shadow",
          "name": "lg",
          "value": "0 10px 15px -3px rgb(0 0 0 / 0.1), 0 4px 6px -4px rgb(0 0 0 / 0.1)"
        },
        {
          "description": "Extra large shadow",
          "name": "xl",
          "value": "0 20px 25px -5px rgb(0 0 0 / 0.1), 0 8px 10px -6px rgb(0 0 0 / 0.1)"
        }
      ],
      "spacing": [
        {
          "description": "Extra small spacing",
          "name": "1",
          "rem_value": 0.25,
          "value": "4px"
        },
        {
          "description": "Small spacing",
          "name": "2",
          "rem_value": 0.5,
          "value": "8px"
        },
        {
          "description": "Medium small spacing",
          "name": "3",
          "rem_value": 0.75,
          "value": "12px"
        },
        {
          "description": "Medium spacing",
          "name": "4",
          "rem_value": 1.0,
          "value": "16px"
        },
        {
          "description": "Medium large spacing",
          "name": "5",
          "rem_value": 1.25,
          "value": "20px"
        },
        {
          "description": "Large spacing",
          "name": "6",
          "rem_value": 1.5,
          "value": "24px"
        },
        {
          "description": "Extra large spacing",
          "name": "8",
          "rem_value": 2.0,
          "value": "32px"
        },
        {
          "description": "2X large spacing",
          "name": "10",
          "rem_value": 2.5,
          "value": "40px"
        },
        {
          "description": "3X large spacing",
          "name": "12",
          "rem_value": 3.0,
          "value": "48px"
        },
        {
          "description": "4X large spacing",
          "name": "16",
          "rem_value": 4.0,
          "value": "64px"
        }
      ],
      "typography": [
        {
          "description": "Extra small text",
          "font_size": "12px",
          "font_weight": "400",
          "letter_spacing": null,
          "line_height": "16px",
          "name": "text-xs"
        },
        {
          "description": "Small text",
          "font_size": "14px",
          "font_weight": "400",
          "letter_spacing": null,
          "line_height": "20px",
          "name": "text-sm"
        },
        {
          "description": "Base text",
          "font_size": "16px",
          "font_weight": "400",
          "letter_spacing": null,
          "line_height": "24px",
          "name": "text-base"
        },
        {
          "description": "Large text",
          "font_size": "18px",
          "font_weight": "400",
          "letter_spacing": null,
          "line_height": "28px",
          "name": "text-lg"
        },
        {
          "description": "Extra large text",
          "font_size": "20px",
          "font_weight": "400",
          "letter_spacing": null,
          "line_height": "28px",
          "name": "text-xl"
        },
        {
          "description": "2X large text",
          "font_size": "24px",
          "font_weight": "700",
          "letter_spacing": "-0.025em",
          "line_height": "32px",
          "name": "text-2xl"
        },
        {
          "description": "3X large text",
          "font_size": "30px",
          "font_weight": "700",
          "letter_spacing": "-0.025em",
          "line_height": "36px",
          "name": "text-3xl"
        }
      ]
    },
    "id": "cab43653-d489-482d-9084-d81fc1586a4b",
    "last_modified": 1779194489551.0,
    "layout": [
      {
        "Container": {
          "animation": null,
          "bindings": {},
          "children": [
            {
              "Text": {
                "animation": null,
                "bindings": {},
                "content": "Login",
                "custom_style": {
                  "background_color": null,
                  "border_color": null,
                  "border_radius": null,
                  "border_width": null,
                  "color": null,
                  "custom_css": null,
                  "display": null,
                  "flex_direction": null,
                  "font_size": null,
                  "font_weight": null,
                  "gap": null,
                  "height": null,
                  "margin": null,
                  "padding": null,
                  "text_align": null,
                  "width": null
                },
                "id": "930bf9fd-fca7-4424-9969-f85a64cabfac",
                "style": "Heading1",
                "tag": "H1"
              }
            },
            {
              "Input": {
                "animation": null,
                "bindings": {},
                "disabled": false,
                "id": "37107507-fcae-423d-9321-107b1d97aeae",
                "input_type": "Email",
                "on_change": null,
                "on_input": null,
                "placeholder": "Email address",
                "required": true,
                "style": {
                  "background_color": null,
                  "border_color": null,
                  "border_radius": null,
                  "border_width": null,
                  "color": null,
                  "custom_css": null,
                  "display": null,
                  "flex_direction": null,
                  "font_size": null,
                  "font_weight": null,
                  "gap": null,
                  "height": null,
                  "margin": null,
                  "padding": null,
                  "text_align": null,
                  "width": null
                }
              }
            },
            {
              "Input": {
                "animation": null,
                "bindings": {},
                "disabled": false,
                "id": "eec9ae19-5603-4e10-86e6-ac1e3d72e045",
                "input_type": "Password",
                "on_change": null,
                "on_input": null,
                "placeholder": "Password",
                "required": true,
                "style": {
                  "background_color": null,
                  "border_color": null,
                  "border_radius": null,
                  "border_width": null,
                  "color": null,
                  "custom_css": null,
                  "display": null,
                  "flex_direction": null,
                  "font_size": null,
                  "font_weight": null,
                  "gap": null,
                  "height": null,
                  "margin": null,
                  "padding": null,
                  "text_align": null,
                  "width": null
                }
              }
            },
            {
              "Button": {
                "animation": null,
                "bindings": {
                  "label": "dynamic_text"
                },
                "disabled": false,
                "id": "50b30547-45fc-4c5d-af19-37baecae7b53",
                "label": "Sign In",
                "on_click": null,
                "size": "Large",
                "style": {
                  "background_color": null,
                  "border_color": null,
                  "border_radius": null,
                  "border_width": null,
                  "color": null,
                  "custom_css": null,
                  "display": null,
                  "flex_direction": null,
                  "font_size": null,
                  "font_weight": null,
                  "gap": null,
                  "height": null,
                  "margin": null,
                  "padding": null,
                  "text_align": null,
                  "width": null
                },
                "variant": "Primary"
              }
            },
            {
              "Text": {
                "animation": null,
                "bindings": {},
                "content": "Forgot your password?",
                "custom_style": {
                  "background_color": null,
                  "border_color": null,
                  "border_radius": null,
                  "border_width": null,
                  "color": null,
                  "custom_css": null,
                  "display": null,
                  "flex_direction": null,
                  "font_size": null,
                  "font_weight": null,
                  "gap": null,
                  "height": null,
                  "margin": null,
                  "padding": null,
                  "text_align": null,
                  "width": null
                },
                "id": "16c7e598-131d-4cdf-a5c1-0379e9e49078",
                "style": "Body",
                "tag": "P"
              }
            }
          ],
          "gap": 16,
          "id": "ab7d2914-6f13-4b0c-ae44-98a5c3c89485",
          "layout": {
            "Flex": {
              "align_items": "Start",
              "direction": "Column",
              "justify_content": "Start",
              "wrap": false
            }
          },
          "on_click": null,
          "padding": {
            "bottom": 32,
            "left": 32,
            "right": 32,
            "top": 32
          },
          "style": {
            "background_color": null,
            "border_color": null,
            "border_radius": null,
            "border_width": null,
            "color": null,
            "custom_css": null,
            "display": null,
            "flex_direction": null,
            "font_size": null,
            "font_weight": null,
            "gap": null,
            "height": null,
            "margin": null,
            "padding": null,
            "text_align": null,
            "width": null
          }
        }
      }
    ],
    "name": "Untitled Project",
    "settings": {
      "auto_save": true,
      "export_preset": "Plain",
      "theme": "Light"
    },
    "variables": [
      {
        "data_type": "String",
        "default_value": "Bound Value",
        "name": "dynamic_text"
      }
    ]
  },
  "7e8705bc-7e67-4d8c-abb7-1c9a1f9572b1": {
    "description": null,
    "design_tokens": {
      "border_radius": [
        {
          "description": "No border radius",
          "name": "none",
          "value": "0px"
        },
        {
          "description": "Small border radius",
          "name": "sm",
          "value": "2px"
        },
        {
          "description": "Medium border radius",
          "name": "md",
          "value": "4px"
        },
        {
          "description": "Large border radius",
          "name": "lg",
          "value": "6px"
        },
        {
          "description": "Extra large border radius",
          "name": "xl",
          "value": "12px"
        },
        {
          "description": "Full border radius",
          "name": "full",
          "value": "9999px"
        }
      ],
      "colors": [
        {
          "description": "Lightest primary blue",
          "name": "primary-50",
          "value": "#eff6ff"
        },
        {
          "description": "Very light primary blue",
          "name": "primary-100",
          "value": "#dbeafe"
        },
        {
          "description": "Primary blue",
          "name": "primary-500",
          "value": "#3b82f6"
        },
        {
          "description": "Dark primary blue",
          "name": "primary-600",
          "value": "#2563eb"
        },
        {
          "description": "Darkest primary blue",
          "name": "primary-900",
          "value": "#1e3a8a"
        },
        {
          "description": "Lightest gray",
          "name": "gray-50",
          "value": "#f9fafb"
        },
        {
          "description": "Very light gray",
          "name": "gray-100",
          "value": "#f3f4f6"
        },
        {
          "description": "Light gray",
          "name": "gray-200",
          "value": "#e5e7eb"
        },
        {
          "description": "Medium light gray",
          "name": "gray-300",
          "value": "#d1d5db"
        },
        {
          "description": "Medium gray",
          "name": "gray-400",
          "value": "#9ca3af"
        },
        {
          "description": "Medium dark gray",
          "name": "gray-500",
          "value": "#6b7280"
        },
        {
          "description": "Dark gray",
          "name": "gray-600",
          "value": "#4b5563"
        },
        {
          "description": "Very dark gray",
          "name": "gray-700",
          "value": "#374151"
        },
        {
          "description": "Darkest gray",
          "name": "gray-800",
          "value": "#1f2937"
        },
        {
          "description": "Black gray",
          "name": "gray-900",
          "value": "#111827"
        },
        {
          "description": "Success green",
          "name": "success-500",
          "value": "#10b981"
        },
        {
          "description": "Warning orange",
          "name": "warning-500",
          "value": "#f59e0b"
        },
        {
          "description": "Error red",
          "name": "error-500",
          "value": "#ef4444"
        },
        {
          "description": "Pure white",
          "name": "white",
          "value": "#ffffff"
        },
        {
          "description": "Pure black",
          "name": "black",
          "value": "#000000"
        }
      ],
      "shadows": [
        {
          "description": "No shadow",
          "name": "none",
          "value": "none"
        },
        {
          "description": "Small shadow",
          "name": "sm",
          "value": "0 1px 2px 0 rgb(0 0 0 / 0.05)"
        },
        {
          "description": "Medium shadow",
          "name": "md",
          "value": "0 4px 6px -1px rgb(0 0 0 / 0.1), 0 2px 4px -2px rgb(0 0 0 / 0.1)"
        },
        {
          "description": "Large shadow",
          "name": "lg",
          "value": "0 10px 15px -3px rgb(0 0 0 / 0.1), 0 4px 6px -4px rgb(0 0 0 / 0.1)"
        },
        {
          "description": "Extra large shadow",
          "name": "xl",
          "value": "0 20px 25px -5px rgb(0 0 0 / 0.1), 0 8px 10px -6px rgb(0 0 0 / 0.1)"
        }
      ],
      "spacing": [
        {
          "description": "Extra small spacing",
          "name": "1",
          "rem_value": 0.25,
          "value": "4px"
        },
        {
          "description": "Small spacing",
          "name": "2",
          "rem_value": 0.5,
          "value": "8px"
        },
        {
          "description": "Medium small spacing",
          "name": "3",
          "rem_value": 0.75,
          "value": "12px"
        },
        {
          "description": "Medium spacing",
          "name": "4",
          "rem_value": 1.0,
          "value": "16px"
        },
        {
          "description": "Medium large spacing",
          "name": "5",
          "rem_value": 1.25,
          "value": "20px"
        },
        {
          "description": "Large spacing",
          "name": "6",
          "rem_value": 1.5,
          "value": "24px"
        },
        {
          "description": "Extra large spacing",
          "name": "8",
          "rem_value": 2.0,
          "value": "32px"
        },
        {
          "description": "2X large spacing",
          "name": "10",
          "rem_value": 2.5,
          "value": "40px"
        },
        {
          "description": "3X large spacing",
          "name": "12",
          "rem_value": 3.0,
          "value": "48px"
        },
        {
          "description": "4X large spacing",
          "name": "16",
          "rem_value": 4.0,
          "value": "64px"
        }
      ],
      "typography": [
        {
          "description": "Extra small text",
          "font_size": "12px",
          "font_weight": "400",
          "letter_spacing": null,
          "line_height": "16px",
          "name": "text-xs"
        },
        {
          "description": "Small text",
          "font_size": "14px",
          "font_weight": "400",
          "letter_spacing": null,
          "line_height": "20px",
          "name": "text-sm"
        },
        {
          "description": "Base text",
          "font_size": "16px",
          "font_weight": "400",
          "letter_spacing": null,
          "line_height": "24px",
          "name": "text-base"
        },
        {
          "description": "Large text",
          "font_size": "18px",
          "font_weight": "400",
          "letter_spacing": null,
          "line_height": "28px",
          "name": "text-lg"
        },
        {
          "description": "Extra large text",
          "font_size": "20px",
          "font_weight": "400",
          "letter_spacing": null,
          "line_height": "28px",
          "name": "text-xl"
        },
        {
          "description": "2X large text",
          "font_size": "24px",
          "font_weight": "700",
          "letter_spacing": "-0.025em",
          "line_height": "32px",
          "name": "text-2xl"
        },
        {
          "description": "3X large text",
          "font_size": "30px",
          "font_weight": "700",
          "letter_spacing": "-0.025em",
          "line_height": "36px",
          "name": "text-3xl"
        }
      ]
    },
    "id": "7e8705bc-7e67-4d8c-abb7-1c9a1f9572b1",
    "last_modified": 1779194505054.0,
    "layout": [
      {
        "Container": {
          "animation": null,
          "bindings": {},
          "children": [
            {
              "Text": {
                "animation": null,
                "bindings": {},
                "content": "Login",
                "custom_style": {
                  "background_color": null,
                  "border_color": null,
                  "border_radius": null,
                  "border_width": null,
                  "color": null,
                  "custom_css": null,
                  "display": null,
                  "flex_direction": null,
                  "font_size": null,
                  "font_weight": null,
                  "gap": null,
                  "height": null,
                  "margin": null,
                  "padding": null,
                  "text_align": null,
                  "width": null
                },
                "id": "2ce8dc93-c10a-4172-9f2d-17405a8efe55",
                "style": "Heading1",
                "tag": "H1"
              }
            },
            {
              "Input": {
                "animation": null,
                "bindings": {},
                "disabled": false,
                "id": "383c6e1f-0682-41e5-a030-adfacb347439",
                "input_type": "Email",
                "on_change": null,
                "on_input": null,
                "placeholder": "Email address",
                "required": true,
                "style": {
                  "background_color": null,
                  "border_color": null,
                  "border_radius": null,
                  "border_width": null,
                  "color": null,
                  "custom_css": null,
                  "display": null,
                  "flex_direction": null,
                  "font_size": null,
                  "font_weight": null,
                  "gap": null,
                  "height": null,
                  "margin": null,
                  "padding": null,
                  "text_align": null,
                  "width": null
                }
              }
            },
            {
              "Input": {
                "animation": null,
                "bindings": {},
                "disabled": false,
                "id": "3f1f2b04-7eb2-4225-ae05-7fb164b774d2",
                "input_type": "Password",
                "on_change": null,
                "on_input": null,
                "placeholder": "Password",
                "required": true,
                "style": {
                  "background_color": null,
                  "border_color": null,
                  "border_radius": null,
                  "border_width": null,
                  "color": null,
                  "custom_css": null,
                  "display": null,
                  "flex_direction": null,
                  "font_size": null,
                  "font_weight": null,
                  "gap": null,
                  "height": null,
                  "margin": null,
                  "padding": null,
                  "text_align": null,
                  "width": null
                }
              }
            },
            {
              "Button": {
                "animation": null,
                "bindings": {
                  "label": "dynamic_text"
                },
                "disabled": false,
                "id": "7c14aab9-c913-4ccc-ab80-d710e2e477a8",
                "label": "Sign In",
                "on_click": null,
                "size": "Large",
                "style": {
                  "background_color": null,
                  "border_color": null,
                  "border_radius": null,
                  "border_width": null,
                  "color": null,
                  "custom_css": null,
                  "display": null,
                  "flex_direction": null,
                  "font_size": null,
                  "font_weight": null,
                  "gap": null,
                  "height": null,
                  "margin": null,
                  "padding": null,
                  "text_align": null,
                  "width": null
                },
                "variant": "Primary"
              }
            },
            {
              "Text": {
                "animation": null,
                "bindings": {},
                "content": "Forgot your password?",
                "custom_style": {
                  "background_color": null,
                  "border_color": null,
                  "border_radius": null,
                  "border_width": null,
                  "color": null,
                  "custom_css": null,
                  "display": null,
                  "flex_direction": null,
                  "font_size": null,
                  "font_weight": null,
                  "gap": null,
                  "height": null,
                  "margin": null,
                  "padding": null,
                  "text_align": null,
                  "width": null
                },
                "id": "8bec6568-b712-49bd-bbb1-30f2eb27a0ee",
                "style": "Body",
                "tag": "P"
              }
            }
          ],
          "gap": 16,
          "id": "7d56fa35-767d-4108-9fc4-b3c85857fd7c",
          "layout": {
            "Flex": {
              "align_items": "Start",
              "direction": "Column",
              "justify_content": "Start",
              "wrap": false
            }
          },
          "on_click": null,
          "padding": {
            "bottom": 32,
            "left": 32,
            "right": 32,
            "top": 32
          },
          "style": {
            "background_color": null,
            "border_color": null,
            "border_radius": null,
            "border_width": null,
            "color": null,
            "custom_css": null,
            "display": null,
            "flex_direction": null,
            "font_size": null,
            "font_weight": null,
            "gap": null,
            "height": null,
            "margin": null,
            "padding": null,
            "text_align": null,
            "width": null
          }
        }
      }
    ],
    "name": "Untitled Project",
    "settings": {
      "auto_save": true,
      "export_preset": "Plain",
      "theme": "Light"
    },
    "variables": [
      {
        "data_type": "String",
        "default_value": "Bound Value",
        "name": "dynamic_text"
      }
    ]
  }
}